{"phone_number": "(512) 715-3000", "indicators": {"readm_30_hip_knee": 5.5, "ed_1b": null, "hai_4_desc": "Not Available", "hai_3_desc": "No Different than National Benchmark", "op_18b": null, "h_hsp_rating_9_10": null, "hai_1_desc": "Not Available", "h_comp_3_a_p": null, "mort_30_pn": 10.8, "h_clean_hsp_a_p": null, "readm_30_pn": 18.0, "hai_4": null, "h_recmnd_dy": null, "hai_2": null, "hai_3": 0.977, "readm_30_ami": null, "hai_1": null, "h_comp_2_a_p": null, "death_from_serious_complications": "Not Available", "serious_complications": "Not Available", "readm_30_hosp_wide": 15.5, "h_quiet_hsp_a_p": null, "mort_30_ami": null, "op_20": null, "readm_30_hf": 21.2, "mort_30_hf": 12.8, "h_comp_1_a_p": null, "hai_2_desc": "Not Available", "comp_hip_knee": 3.3}, "provider_number": "451365", "address": "3201 S. Water St.", "emergency_services": "Yes", "city": "Burnet", "name": "Seton Highland Lakes", "url": "seton-highland-lakes", "zipcode": "78611", "longitude": "-98.3842388379997", "hospital ownership": "Nonprofit - Church", "old_url": "seton-highland-lakes", "latitude": "30.80165340500048", "_id": "451365", "type": "Critical Access"}