{"phone_number": "903-315-2000", "longitude": "-94.73134817899967", "address": "700 East Marshall Avenue", "emergency_services": "Yes", "city": "Longview", "name": "Good Shepherd Medical Center", "url": "good-shepherd-medical-center", "data": {"emergency_rates": {"OP 18": 139, "ED1": 241, "Door to diagnostic eval": 46}, "quality": {"always_quiet_at_night": 70, "rating_9_or_10": 71, "doctors_always_communicate_well": 82, "nurses_always_communicate_well": 78, "always_received_help": 66}, "death_rates": {"mort_30_pn_performance_rate": 0.8815, "mort_30_ami_performance_rate": 0.8605, "mort_30_hf_performance_rate": 0.8937}, "complications_rates": {"death_from_serious_complications": "No Different than U.S. National Rate", "serious_complications": "No Different than U.S. National Rate"}, "readmission_rates": {"rr_from_pn": 19.8, "rr_from_ha": 17.7, "rr_from_k_or_n": null, "rr_from_hf": 23.8}}, "zipcode": "75601", "provider_number": "450037", "hospital ownership": "Voluntary Non Profit   Private", "state": "TX", "latitude": "32.50147763600046", "_id": 4046, "type": "Acute Care Hospitals"}