{"phone_number": "956-487-5561", "longitude": "-98.79654943099968", "address": "128  N Fm Rd 3167", "emergency_services": "Yes", "city": "Rio Grande City", "name": "Starr County Memorial Hospital", "url": "starr-county-memorial-hospital", "data": {"emergency_rates": {"door_to_diagnostic_eval": 26, "ed1": 389, "op_18": 283}, "quality": {"always_quiet_at_night": 65, "rating_9_or_10": 61, "doctors_always_communicate_well": 86, "nurses_always_communicate_well": 79, "always_received_help": 67}, "death_rates": {}, "complications_rates": {"death_from_serious_complications": "Not Available", "serious_complications": "No Different than U.S. National Rate"}, "readmission_rates": {"rr_from_pn": 19.2, "rr_from_ha": 18.0, "rr_from_k_or_n": null, "rr_from_hf": 24.4}}, "zipcode": "78582", "provider_number": "450654", "hospital ownership": "Government   Hospital District Or Authority", "state": "TX", "latitude": "26.376012012000444", "_id": 4206, "type": "Acute Care Hospitals"}