{"phone_number": "325-844-2561", "longitude": "-101.46171618399967", "address": "805 North Main", "emergency_services": "Yes", "city": "Big Lake", "name": "Reagan Memorial Hospital", "url": "reagan-memorial-hospital", "data": {"emergency_rates": {"OP 18": null, "ED1": null, "Door to diagnostic eval": null}, "quality": {"always_quiet_at_night": 74, "rating_9_or_10": 76, "doctors_always_communicate_well": 84, "nurses_always_communicate_well": 100, "always_received_help": 100}, "death_rates": {}, "complications_rates": {"death_from_serious_complications": "Not Available", "serious_complications": "Not Available"}, "readmission_rates": {"rr_from_pn": null, "rr_from_ha": null, "rr_from_k_or_n": null, "rr_from_hf": null}}, "zipcode": "76932", "provider_number": "451301", "hospital ownership": "Government   Hospital District Or Authority", "state": "TX", "latitude": "31.197585137000488", "_id": 4302, "type": "Critical Access Hospitals"}