{"phone_number": "903-541-4500", "longitude": "-95.2510389149997", "address": "2026 S Jackson Street", "emergency_services": "Yes", "city": "Jacksonville", "name": "Mother Frances Hospital Jacksonville", "url": "mother-frances-hospital-jacksonville", "data": {"emergency_rates": {"ED1": null}, "quality": {"always_quiet_at_night": null, "rating_9_or_10": null, "doctors_always_communicate_well": null, "nurses_always_communicate_well": null, "always_received_help": null}, "death_rates": {}, "complications_rates": {"death_from_serious_complications": "Not Available", "serious_complications": "Not Available"}, "readmission_rates": {"rr_from_pn": 18.1, "rr_from_ha": null, "rr_from_k_or_n": null, "rr_from_hf": 21.9}}, "zipcode": "75766", "provider_number": "451319", "hospital ownership": "Voluntary Non Profit   Private", "state": "TX", "latitude": "31.939444942000478", "_id": 4313, "type": "Critical Access Hospitals"}