{"phone_number": "(512) 850-5000", "longitude": "-97.38499668099968", "address": "3533 S. Alameda/P.O. Box 6530", "emergency_services": "Yes", "city": "Corpus Christi", "name": "Driscoll Childrens Hospital", "url": "driscoll-childrens-hospital", "data": {"emergency_rates": {"ed_1b": null}, "quality": {"h_quiet_hsp_a_p": null, "h_hsp_rating_9_10": null, "h_recmnd_dy": null, "h_comp_2_a_p": null, "h_comp_3_a_p": null, "h_comp_1_a_p": null, "h_clean_hsp_a_p": null}, "associated_infections": {"hai_4_desc": "Not Available", "hai_3_desc": "Not Available", "hai_1_desc": "Not Available", "hai_2_desc": "Not Available", "hai_4": "Not Available", "hai_2": "Not Available", "hai_3": "Not Available", "hai_1": "Not Available"}, "complications_rates": {"death_from_serious_complications": "Not Available", "serious_complications": "Not Available"}, "outcomes": {"mort_30_pn": null, "readm_30_hip_knee": null, "mort_30_hf": null, "readm_30_hosp_wide": null, "mort_30_ami": null, "readm_30_ha": null, "readm_30_pn": null, "comp_hip_knee": null, "readm_30_hf": null}}, "zipcode": "78411", "provider_number": "453301", "hospital ownership": "Voluntary Non Profit   Other", "state": "TX", "latitude": "27.74926046200045", "_id": 4355, "type": "Childrens"}