{"phone_number": "(940) 549-3400", "indicators": {"readm_30_hip_knee": 5.1, "ed_1b": 216, "hai_4_desc": "Not Available", "hai_3_desc": "Not Available", "op_18b": 110, "h_hsp_rating_9_10": 75, "hai_1_desc": "Not Available", "h_comp_3_a_p": 81, "mort_30_pn": 10.8, "h_clean_hsp_a_p": 63, "readm_30_pn": 15.4, "hai_4": null, "h_recmnd_dy": 81, "hai_2": null, "hai_3": null, "readm_30_ami": null, "hai_1": null, "h_comp_2_a_p": 91, "death_from_serious_complications": "Not Available", "serious_complications": "No Different than the National Rate", "readm_30_hosp_wide": 15.0, "h_quiet_hsp_a_p": 73, "mort_30_ami": null, "op_20": 32, "readm_30_hf": 22.3, "mort_30_hf": 13.0, "h_comp_1_a_p": 83, "hai_2_desc": "Not Available", "comp_hip_knee": 3.0}, "provider_number": "450085", "address": "1301 Montgomery Road", "emergency_services": "Yes", "city": "Graham", "name": "Graham Regional Medical Center", "url": "graham-regional-medical-center", "zipcode": "76450", "longitude": "-98.58576011499969", "hospital ownership": "Government - Local", "old_url": "graham-regional-medical-center", "latitude": "33.08987958600045", "_id": "450085", "type": "Acute Care"}