{"phone_number": "(713) 792-2121", "indicators": {}, "provider_number": "450076", "address": "1515 Holcombe Blvd.", "emergency_services": "Yes", "city": "Houston", "name": "University Of Texas M D Anderson Cancer Center,The", "url": "university-of-texas-m-d-anderson-cancer-center-the", "zipcode": "77030", "longitude": "-95.39693895799968", "hospital ownership": "Government - State", "old_url": "university-of-texas-m-d-anderson-cancer-center-the", "latitude": "29.706352887000435", "_id": "450076", "type": "Acute Care"}