{"phone_number": "(281) 333-5503", "indicators": {"readm_30_hip_knee": 4.7, "ed_1b": 335, "hai_4_desc": "Not Available", "hai_3_desc": "No Different than U.S. National Benchmark", "op_18b": 159, "h_hsp_rating_9_10": 74, "hai_1_desc": "No Different than U.S. National Benchmark", "h_comp_3_a_p": 66, "mort_30_pn": 12.0, "h_clean_hsp_a_p": 73, "readm_30_pn": 18.4, "hai_4": null, "h_recmnd_dy": 78, "hai_2": 0.914, "hai_3": 0.0, "readm_30_ami": 18.8, "hai_1": 0.554, "h_comp_2_a_p": 75, "death_from_serious_complications": "Number of Cases Too Small", "serious_complications": "No Different than the National Rate", "readm_30_hosp_wide": 15.1, "h_quiet_hsp_a_p": 57, "mort_30_ami": 15.6, "op_20": 26, "readm_30_hf": 23.6, "mort_30_hf": 12.0, "h_comp_1_a_p": 76, "hai_2_desc": "No Different than U.S. National Benchmark", "comp_hip_knee": 2.9}, "provider_number": "450709", "address": "18300 St. John Drive", "emergency_services": "Yes", "city": "Nassau Bay", "name": "Christus St John Hospital", "url": "christus-st-john-hospital", "zipcode": "77058", "longitude": "-95.0848286539997", "hospital ownership": "Nonprofit - Church", "old_url": "christus-st-john-hospital", "latitude": "29.54885890300045", "_id": "450709", "type": "Acute Care"}