{"phone_number": "(713) 652-3800", "longitude": "-95.40077819599969", "address": "7501 Fannin", "emergency_services": "Yes", "city": "Houston", "name": "University General Hospital", "url": "university-general-hospital", "data": {"emergency_rates": {"door_to_diagnostic_eval": 46, "ed1": 225, "op_18": 166}, "quality": {"always_quiet_at_night": 74, "rating_9_or_10": 72, "doctors_always_communicate_well": 83, "nurses_always_communicate_well": 72, "always_received_help": 56}, "death_rates": {"mort_30_pn_performance_rate": 0.8761, "mort_30_ami_performance_rate": 0.8525, "mort_30_hf_performance_rate": 0.8858}, "complications_rates": {"death_from_serious_complications": "No Different than U.S. National Rate", "serious_complications": "No Different than U.S. National Rate"}, "readmission_rates": {"rr_from_pn": null, "rr_from_ha": null, "rr_from_k_or_n": null, "rr_from_hf": 21.7}}, "zipcode": "77054", "provider_number": "670019", "hospital ownership": "Proprietary", "state": "TX", "latitude": "29.693011021000473", "_id": 4819, "type": "Acute Care Hospitals"}